yomito/__init__.py
yomito/core.py
yomito/ocr/__init__.py
yomito/ocr/enhance.py
yomito/ocr/models.py
yomito/ocr/tesseract.py
yomito-1.3.0.dist-info/licenses/LICENSE
yomito-1.3.0.dist-info/METADATA
yomito-1.3.0.dist-info/WHEEL
yomito-1.3.0.dist-info/top_level.txt
yomito-1.3.0.dist-info/RECORD
