Metadata-Version: 2.4
Name: yomito
Version: 1.3.0
Summary: High-accuracy OCR library with intelligent auto-optimization
Author: カネキ
License: MIT
Project-URL: Homepage, https://github.com/fabfawufawd/yomito
Project-URL: Repository, https://github.com/fabfawufawd/yomito
Project-URL: Issues, https://github.com/fabfawufawd/yomito/issues
Project-URL: Documentation, https://github.com/fabfawufawd/yomito#readme
Keywords: ocr,tesseract,image,text-recognition,computer-vision
Classifier: Development Status :: 4 - Beta
Classifier: Intended Audience :: Developers
Classifier: License :: OSI Approved :: MIT License
Classifier: Operating System :: OS Independent
Classifier: Programming Language :: Python :: 3
Classifier: Programming Language :: Python :: 3.8
Classifier: Programming Language :: Python :: 3.9
Classifier: Programming Language :: Python :: 3.10
Classifier: Programming Language :: Python :: 3.11
Classifier: Programming Language :: Python :: 3.12
Classifier: Topic :: Scientific/Engineering :: Image Recognition
Classifier: Topic :: Software Development :: Libraries :: Python Modules
Classifier: Topic :: Multimedia :: Graphics :: Capture :: Scanners
Requires-Python: >=3.8
License-File: LICENSE
Requires-Dist: Pillow>=8.0.0
Requires-Dist: numpy>=1.20.0
Provides-Extra: dev
Requires-Dist: pytest>=6.0; extra == "dev"
Requires-Dist: pytest-cov; extra == "dev"
Requires-Dist: black; extra == "dev"
Requires-Dist: flake8; extra == "dev"
Requires-Dist: mypy; extra == "dev"
Dynamic: license-file
